gsvdm2py/__init__.py
gsvdm2py/gsvd.py
gsvdm2py-0.0.1.dist-info/LICENSE
gsvdm2py-0.0.1.dist-info/METADATA
gsvdm2py-0.0.1.dist-info/WHEEL
gsvdm2py-0.0.1.dist-info/top_level.txt
gsvdm2py-0.0.1.dist-info/RECORD
